metacore/__init__.py
metacore/app/__init__.py
metacore/app/ad_segment.py
metacore/app/segment.py
metacore/open_clip/__init__.py
metacore/open_clip/bpe_simple_vocab_16e6.txt.gz
metacore/open_clip/coca_model.py
metacore/open_clip/constants.py
metacore/open_clip/factory.py
metacore/open_clip/generation_utils.py
metacore/open_clip/hf_configs.py
metacore/open_clip/hf_model.py
metacore/open_clip/loss.py
metacore/open_clip/model.py
metacore/open_clip/modified_resnet.py
metacore/open_clip/openai.py
metacore/open_clip/pretrained.py
metacore/open_clip/push_to_hf_hub.py
metacore/open_clip/timm_model.py
metacore/open_clip/tokenizer.py
metacore/open_clip/transform.py
metacore/open_clip/transformer.py
metacore/open_clip/utils.py
metacore/open_clip/version.py
metacore/open_clip/model_configs/RN101-quickgelu.json
metacore/open_clip/model_configs/RN101.json
metacore/open_clip/model_configs/RN50-quickgelu.json
metacore/open_clip/model_configs/RN50.json
metacore/open_clip/model_configs/RN50x16.json
metacore/open_clip/model_configs/RN50x4.json
metacore/open_clip/model_configs/RN50x64.json
metacore/open_clip/model_configs/ViT-B-16-plus-240.json
metacore/open_clip/model_configs/ViT-B-16-plus.json
metacore/open_clip/model_configs/ViT-B-16.json
metacore/open_clip/model_configs/ViT-B-32-plus-256.json
metacore/open_clip/model_configs/ViT-B-32-quickgelu.json
metacore/open_clip/model_configs/ViT-B-32.json
metacore/open_clip/model_configs/ViT-H-14.json
metacore/open_clip/model_configs/ViT-H-16.json
metacore/open_clip/model_configs/ViT-L-14-280.json
metacore/open_clip/model_configs/ViT-L-14-336.json
metacore/open_clip/model_configs/ViT-L-14.json
metacore/open_clip/model_configs/ViT-L-16-320.json
metacore/open_clip/model_configs/ViT-L-16.json
metacore/open_clip/model_configs/ViT-M-16-alt.json
metacore/open_clip/model_configs/ViT-M-16.json
metacore/open_clip/model_configs/ViT-M-32-alt.json
metacore/open_clip/model_configs/ViT-M-32.json
metacore/open_clip/model_configs/ViT-S-16-alt.json
meta_core-3.8.15.dist-info/METADATA
meta_core-3.8.15.dist-info/WHEEL
meta_core-3.8.15.dist-info/top_level.txt
meta_core-3.8.15.dist-info/zip-safe
meta_core-3.8.15.dist-info/RECORD
