Metadata-Version: 2.1
Name: meta-core
Version: 3.8.15
Summary: Meta Core Toolkit
Home-page: https://github.com/CachCheng/cvreid
Author: CachCheng
Author-email: tkggpdc2007@163.com
License: Apache-2.0
Requires-Dist: opencv-python
Requires-Dist: setuptools
Requires-Dist: numpy
Requires-Dist: pillow
Requires-Dist: torch
Requires-Dist: ftfy
Requires-Dist: regex
